motypst/__init__.py
motypst-0.1.0.dist-info/WHEEL
motypst-0.1.0.dist-info/entry_points.txt
motypst-0.1.0.dist-info/METADATA
motypst-0.1.0.dist-info/RECORD
