Metadata-Version: 2.3
Name: motypst
Version: 0.1.0
Summary: A Typst widget for marimo notebooks
Author: Hannes Knoll
Author-email: Hannes Knoll <git@hannesknoll.de>
Requires-Dist: marimo>=0.19.6
Requires-Dist: typst>=0.14.7
Requires-Python: >=3.13
